{
    "round": "第2113回",
    "date": "2026/06/22",
    "main_nums": [
        "02",
        "05",
        "32",
        "36",
        "38",
        "42"
    ],
    "bonus": "14",
    "carryover": "744,495,484円",
    "prizes": [
        {
            "grade": "1等",
            "winners": "該当なし",
            "prize": "該当なし"
        },
        {
            "grade": "2等",
            "winners": "8口",
            "prize": "10,842,600円"
        },
        {
            "grade": "3等",
            "winners": "225口",
            "prize": "416,300円"
        },
        {
            "grade": "4等",
            "winners": "12,885口",
            "prize": "7,600円"
        },
        {
            "grade": "5等",
            "winners": "213,988口",
            "prize": "1,000円"
        }
    ],
    "predictions": [
        {
            "name": "予想A",
            "nums": "04, 14, 21, 23, 29, 33",
            "hit": 0
        },
        {
            "name": "予想B",
            "nums": "07, 09, 13, 14, 22, 23",
            "hit": 0
        },
        {
            "name": "予想C",
            "nums": "03, 09, 14, 22, 23, 29",
            "hit": 0
        },
        {
            "name": "予想D",
            "nums": "07, 09, 13, 14, 22, 31",
            "hit": 0
        },
        {
            "name": "予想E",
            "nums": "13, 14, 23, 24, 29, 35",
            "hit": 0
        }
    ]
}